gwastic_desktop/.work_directory.1_GtG.get_gtg/0.1.p
gwastic_desktop/.work_directory.1_GtG.get_gtg/0.2.p
gwastic_desktop/.work_directory.1_GtG.get_gtg/0.5.p
gwastic_desktop/.work_directory.1_GtG.get_gtg/1.2.p
gwastic_desktop/.work_directory.1_GtG.get_gtg/1.5.p
gwastic_desktop/.work_directory.1_GtG.get_gtg/2.5.p
gwastic_desktop/.work_directory.1_GtG.get_gtg/3.5.p
gwastic_desktop/.work_directory.1_GtG.get_gtg/4.5.p
gwastic_desktop/gp_pipeline.py
gwastic_desktop/gwas_ai.py
gwastic_desktop/gwas_pipeline.py
gwastic_desktop/helpers.py
gwastic_desktop/images/geno.gif
gwastic_desktop/images/gui.gif
gwastic_desktop/images/gui.PNG
gwastic_desktop/images/pheno.gif
gwastic_desktop/LICENSE
gwastic_desktop/linux/LICENSE
gwastic_desktop/linux/plink
gwastic_desktop/linux/prettify
gwastic_desktop/mac/LICENSE
gwastic_desktop/mac/plink
gwastic_desktop/mac/prettify
gwastic_desktop/mac/toy.map
gwastic_desktop/mac/toy.ped
gwastic_desktop/main_gui.py
gwastic_desktop/plot_pipeline.py
gwastic_desktop/requirements.txt
gwastic_desktop/settings.ini
gwastic_desktop/test.ttf
gwastic_desktop/windows/plink.exe
gwastic_desktop-0.6.0.dist-info/entry_points.txt
gwastic_desktop-0.6.0.dist-info/METADATA
gwastic_desktop-0.6.0.dist-info/WHEEL
gwastic_desktop-0.6.0.dist-info/RECORD
