Metadata-Version: 2.1
Name: gwastic-desktop
Version: 0.6.0
Summary: GWAS software that combines traditional statistical methods with the power of Artificial Intelligence
Author: Stefanie Lueck
Author-email: lueck@ipk-gatersleben.de
Requires-Python: >=3.9,<4.0
Classifier: Programming Language :: Python :: 3
Classifier: Programming Language :: Python :: 3.9
Classifier: Programming Language :: Python :: 3.10
Classifier: Programming Language :: Python :: 3.11
Requires-Dist: dearpygui
Requires-Dist: dearpygui-ext
Requires-Dist: fastlmm
Requires-Dist: geneview
Requires-Dist: matplotlib
Requires-Dist: pandas
Requires-Dist: scikit-learn
Requires-Dist: scipy
Requires-Dist: xgboost
